mrkv.py
setup.cfg
setup.py
mrkv.egg-info/PKG-INFO
mrkv.egg-info/SOURCES.txt
mrkv.egg-info/dependency_links.txt
mrkv.egg-info/not-zip-safe
mrkv.egg-info/requires.txt
mrkv.egg-info/top_level.txt
test/test.py