Metadata-Version: 1.0
Name: mrkv
Version: 0.0.1
Summary: Tiny Markov chain library
Home-page: http://github.com/erdiaker/mrkv
Author: Erdi Aker
Author-email: erdiaker@gmail.com
License: MIT
Platform: UNKNOWN
